mastermind/__init__.py
mastermind/__main__.py
mastermind/mastermind.py
mastermind/params.py
open_mastermind-0.2.0.dist-info/LICENSE
open_mastermind-0.2.0.dist-info/METADATA
open_mastermind-0.2.0.dist-info/WHEEL
open_mastermind-0.2.0.dist-info/entry_points.txt
open_mastermind-0.2.0.dist-info/top_level.txt
open_mastermind-0.2.0.dist-info/RECORD
