Metadata-Version: 2.1
Name: open-mastermind
Version: 0.2.0
Summary: A terminal-based code-breaking game Mastermind
Home-page: https://github.com/philshem/open-mastermind
Author: Philip Shemella
Author-email: philshem@pm.me
License: UNKNOWN
Keywords: puz mastermind code-breaking puzzle game
Platform: UNKNOWN
Classifier: Environment :: Console :: Curses
Classifier: License :: OSI Approved :: MIT License
Classifier: Programming Language :: Python :: 3
Classifier: Topic :: Games/Entertainment :: Puzzle Games
Requires-Python: >=2.7
Requires-Dist: colorama
